{"doc_id": "news_973b1856fcc933a9", "content": "\n=== NEWS ARTICLE ===\nTitle: Record IPO boom: Over 700 issues raise  \u20b93.8 trillion in two years, young companies lead listings: Report\nSource: LiveMint - Markets\nPublished: 2025-12-28 02:29\nRelated Stocks: RELIANCE\nCategories: markets\n\nSummary:\nIn 2025, the Indian IPO market thrived with 365 companies raising \u20b91.95 trillion, driven by strong investor interest across sectors. Retail and foreign investors contributed significantly, highlighting a trend toward diversification and increased participation from younger firms.\n\nSentiment: positive\nURL: https://www.livemint.com/market/stock-market-news/record-ipo-boom-over-700-issues-raise-rs-3-8-trillion-in-two-years-young-companies-lead-listings-report-11766822302518.html\n", "doc_type": "news", "symbol": "RELIANCE", "source": "LiveMint - Markets", "metadata": "{\"title\": \"Record IPO boom: Over 700 issues raise  \\u20b93.8 trillion in two years, young companies lead listings: Report\", \"sentiment\": \"positive\", \"symbols\": [\"RELIANCE\"], \"url\": \"https://www.livemint.com/market/stock-market-news/record-ipo-boom-over-700-issues-raise-rs-3-8-trillion-in-two-years-young-companies-lead-listings-report-11766822302518.html\"}", "timestamp": 1766942720002}