{"doc_id": "news_694bc065d71d105c", "content": "\n=== NEWS ARTICLE ===\nTitle: Taking Stock: Market fails to hold on to day#39;s gains, ends marginally higher\nSource: Moneycontrol - Markets\nPublished: 2024-04-23 10:16\nRelated Stocks: HCLTECH, SUNPHARMA, RELIANCE, BHARTIARTL, MARUTI\nCategories: markets\n\nSummary:\nGrasim Industries, Bharti Airtel, Nestle India, Maruti Suzuki and HCL Technologies were the biggest Nifty gainers, while losers included Sun Pharma, BPCL, Reliance Industries, MM and Hindalco Industries\n\nSentiment: positive\nURL: https://www.moneycontrol.com/news/local-markets/taking-stock-market-fails-to-holdto-day39s-gains-ends-marginally-higher_17531871.html\n", "doc_type": "news", "symbol": "HCLTECH", "source": "Moneycontrol - Markets", "metadata": "{\"title\": \"Taking Stock: Market fails to hold on to day#39;s gains, ends marginally higher\", \"sentiment\": \"positive\", \"symbols\": [\"HCLTECH\", \"SUNPHARMA\", \"RELIANCE\", \"BHARTIARTL\", \"MARUTI\"], \"url\": \"https://www.moneycontrol.com/news/local-markets/taking-stock-market-fails-to-holdto-day39s-gains-ends-marginally-higher_17531871.html\"}", "timestamp": 1766942719521}