{"doc_id": "news_9aed3f3f6331f9e3", "content": "\n=== NEWS ARTICLE ===\nTitle: ITC share price down 12% year-to-date; should investors buy, sell, or hold this value stock?\nSource: LiveMint - Markets\nPublished: 2025-12-28 10:33\nRelated Stocks: ITC\nCategories: markets\n\nSummary:\nITC shares have dropped 12% this year, prompting investors to reconsider their strategies. Experts weigh in on key support levels and resistance zones, offering insights into whether it's time to buy, sell, or hold this value stock amidst market volatility.\n\nSentiment: neutral\nURL: https://www.livemint.com/market/stock-market-news/itc-share-price-down-12-year-to-date-should-investors-buy-sell-or-hold-this-value-stock-11766915843271.html\n", "doc_type": "news", "symbol": "ITC", "source": "LiveMint - Markets", "metadata": "{\"title\": \"ITC share price down 12% year-to-date; should investors buy, sell, or hold this value stock?\", \"sentiment\": \"neutral\", \"symbols\": [\"ITC\"]}", "timestamp": 1766942773424}