{"doc_id": "news_a4129fe40b56d61d", "content": "\n=== NEWS ARTICLE ===\nTitle: Retail frenzy drives 61 SME IPOs to 100\u20131,000x subscriptions in 2025; 15 turn multibaggers\nSource: LiveMint - Markets\nPublished: 2025-12-28 05:32\nRelated Stocks: RELIANCE, LT\nCategories: markets\n\nSummary:\nThe IPO market thrived in 2025, with 365 offerings raising \u20b91.95 trillion and many SME issues seeing subscriptions over 100 times. While some stocks delivered substantial returns, most listings failed to maintain initial gains, exposing the gap between investor optimism and actual performance.\n\nSentiment: neutral\nURL: https://www.livemint.com/market/stock-market-news/retail-frenzy-drives-61-sme-ipos-to-100-1-000x-subscriptions-in-2025-15-turn-multibaggers-11766893473271.html\n", "doc_type": "news", "symbol": "RELIANCE", "source": "LiveMint - Markets", "metadata": "{\"title\": \"Retail frenzy drives 61 SME IPOs to 100\\u20131,000x subscriptions in 2025; 15 turn multibaggers\", \"sentiment\": \"neutral\", \"symbols\": [\"RELIANCE\", \"LT\"], \"url\": \"https://www.livemint.com/market/stock-market-news/retail-frenzy-drives-61-sme-ipos-to-100-1-000x-subscriptions-in-2025-15-turn-multibaggers-11766893473271.html\"}", "timestamp": 1766942719915}